freellm/__init__.py
freellm/__main__.py
freellm/core.py
freellm-1.0.2.dist-info/licenses/LICENSE
freellm-1.0.2.dist-info/METADATA
freellm-1.0.2.dist-info/WHEEL
freellm-1.0.2.dist-info/entry_points.txt
freellm-1.0.2.dist-info/top_level.txt
freellm-1.0.2.dist-info/RECORD
