Metadata-Version: 2.4
Name: freellm
Version: 1.0.2
Summary: The simplest Python client for free access to top-tier AI models (GPT-4.1 Nano, DeepSeek, Gemini Flash, Claude Haiku)
Home-page: https://github.com/IMApurbo/freellm
Author: AKM Korishee Apurbo
Author-email: bandinvisible8@gmail.com
License: MIT
Keywords: llm ai chatbot free gpt deepseek gemini claude
Classifier: Programming Language :: Python :: 3
Classifier: Programming Language :: Python :: 3.8
Classifier: Programming Language :: Python :: 3.9
Classifier: Programming Language :: Python :: 3.10
Classifier: Programming Language :: Python :: 3.11
Classifier: Programming Language :: Python :: 3.12
Classifier: License :: OSI Approved :: MIT License
Classifier: Operating System :: OS Independent
Classifier: Topic :: Scientific/Engineering :: Artificial Intelligence
Classifier: Intended Audience :: Developers
Classifier: Intended Audience :: End Users/Desktop
Requires-Python: >=3.8
License-File: LICENSE
Requires-Dist: requests>=2.25.0
Dynamic: author
Dynamic: author-email
Dynamic: classifier
Dynamic: description
Dynamic: description-content-type
Dynamic: home-page
Dynamic: keywords
Dynamic: license
Dynamic: license-file
Dynamic: requires-dist
Dynamic: requires-python
Dynamic: summary
